README.md
setup.py
mbanc_hello_world.egg-info/PKG-INFO
mbanc_hello_world.egg-info/SOURCES.txt
mbanc_hello_world.egg-info/dependency_links.txt
mbanc_hello_world.egg-info/top_level.txt
sample_package/__init__.py
sample_package/sample.py